LICENSE
README.md
setup.py
DataStructure/CounterHashMap.py
DataStructure/Stack.py
DataStructure/__init__.py
DataStructure/Cache/LRUCache.py
DataStructure/Cache/__init__.py
DataStructure/Heap/Heap.py
DataStructure/Heap/HeapNode.py
DataStructure/Heap/MaxHeap.py
DataStructure/Heap/MinHeap.py
DataStructure/Heap/__init__.py
DataStructure/Tree/AvlTree.py
DataStructure/Tree/AvlTreeNode.py
DataStructure/Tree/BTree.py
DataStructure/Tree/BTreeNode.py
DataStructure/Tree/Tree.py
DataStructure/Tree/TreeNode.py
DataStructure/Tree/__init__.py
NlpToolkit_DataStructure.egg-info/PKG-INFO
NlpToolkit_DataStructure.egg-info/SOURCES.txt
NlpToolkit_DataStructure.egg-info/dependency_links.txt
NlpToolkit_DataStructure.egg-info/top_level.txt