Metadata-Version: 2.1
Name: NlpToolkit-DataStructure
Version: 1.0.13
Summary: Simple Data Structures Library
Home-page: https://github.com/StarlangSoftware/DataStructure-Py
Author: olcaytaner
Author-email: olcay.yildiz@ozyegin.edu.tr
License: UNKNOWN
Platform: UNKNOWN
License-File: LICENSE
